{
  "port": "3000",
  "adminAccount": "admin@cnabcpm.com",
  "closeRegister":true,
  "db": {
    "servername": "yapi-mongo",
    "DATABASE": "yapi",
    "port": 27017,
    "user": "yapi",
    "pass": "yapi",
    "authSource": "admin"
  },
  "mail": {
    "enable": true,
    "host": "smtp.exmail.qq.com",
    "port": 25,
    "from": "notification@cnabcpm.com",
    "auth": {
      "user": "notification@cnabcpm.com",
      "pass": "4GBjqr0KIl3bUXk0"
    }
  },
  "ldapLogin": {
    "enable": true,
    "server": "ldap://192.168.5.100:389",
    "baseDn": "cn=admin,dc=cnabc-inc,dc=com",
    "bindPassword": "iYI0H1S#tweQD!7",
    "searchDn": "dc=cnabc-inc,dc=com",
    "searchStandard": "uid",
    "emailPostfix": "@cnabcpm.com",
    "emailKey": "uid",
    "usernameKey": "uid"
  }
}